LICENSE
MANIFEST.in
README.md
pyproject.toml
requirements-dev.txt
requirements.txt
setup.py
dph_services/__init__.py
dph_services/common.py
dph_services/common_constants.py
dph_services/dph_v1.py
dph_services/version.py
dph_services.egg-info/PKG-INFO
dph_services.egg-info/SOURCES.txt
dph_services.egg-info/dependency_links.txt
dph_services.egg-info/requires.txt
dph_services.egg-info/top_level.txt
dph_services.egg-info/zip-safe