Metadata-Version: 2.4
Name: dph-services
Version: 1.5.0
Summary: Python client library for DPH Services
Home-page: https://github.com/IBM/data-product-exchange-python-sdk
Author: IBM
Author-email: selva.kumar.jothi.arumugam@ibm.com
License: Apache 2.0
Keywords: dph_services
Classifier: Programming Language :: Python
Classifier: Programming Language :: Python :: 3
Classifier: Programming Language :: Python :: 3.7
Classifier: Programming Language :: Python :: 3.8
Classifier: Programming Language :: Python :: 3.9
Classifier: Programming Language :: Python :: 3.10
Classifier: Programming Language :: Python :: 3.11
Classifier: Programming Language :: Python :: 3.12
Classifier: Development Status :: 4 - Beta
Classifier: Intended Audience :: Developers
Classifier: License :: OSI Approved :: Apache Software License
Classifier: Operating System :: OS Independent
Classifier: Topic :: Software Development :: Libraries :: Python Modules
Classifier: Topic :: Software Development :: Libraries :: Application Frameworks
License-File: LICENSE
Requires-Dist: requests<3.0.0,>=2.32.4
Requires-Dist: urllib3>=2.2.3
Requires-Dist: python_dateutil<3.0.0,>=2.5.3
Requires-Dist: ibm_cloud_sdk_core<4.0.0,>=3.16.7
Dynamic: author
Dynamic: author-email
Dynamic: classifier
Dynamic: description
Dynamic: description-content-type
Dynamic: home-page
Dynamic: keywords
Dynamic: license
Dynamic: license-file
Dynamic: requires-dist
Dynamic: summary
